ScratchEncoder/__init__.py
ScratchEncoder/main.py
ScratchEncoder-0.1.5.dist-info/LICENSE.txt
ScratchEncoder-0.1.5.dist-info/METADATA
ScratchEncoder-0.1.5.dist-info/WHEEL
ScratchEncoder-0.1.5.dist-info/top_level.txt
ScratchEncoder-0.1.5.dist-info/RECORD
