Metadata-Version: 2.1
Name: ScratchEncoder
Version: 0.1.5
Summary: Scratch Encoder
Home-page: https://github.com/The-Cloud-Dev/ScratchEncoder
Author: TheCloudDev
License: MIT
Platform: UNKNOWN
Classifier: Programming Language :: Python :: 3
Classifier: License :: OSI Approved :: MIT License
Classifier: Operating System :: OS Independent
Requires-Python: >=3.6
